activeworkflow_agent/__init__.py
activeworkflow_agent-0.1.dist-info/LICENSE
activeworkflow_agent-0.1.dist-info/METADATA
activeworkflow_agent-0.1.dist-info/WHEEL
activeworkflow_agent-0.1.dist-info/top_level.txt
activeworkflow_agent-0.1.dist-info/RECORD
