Metadata-Version: 2.1
Name: activeworkflow-agent
Version: 0.1
Summary: Helper library for writing ActiveWorkflow agents
Home-page: https://github.com/automaticmode/activeworkflow-agent-python
Author: Automatic Mode Labs
Author-email: info@automaticmode.com
License: MIT
Platform: UNKNOWN
Classifier: Development Status :: 3 - Alpha
Classifier: Intended Audience :: Developers
Classifier: License :: OSI Approved :: MIT License
Classifier: Programming Language :: Python :: 3
Classifier: Programming Language :: Python :: 3.7
Classifier: Programming Language :: Python :: 3.8
Classifier: Programming Language :: Python :: 3.9
Provides-Extra: test
Requires-Dist: pytest ; extra == 'test'
Requires-Dist: schema ; extra == 'test'
